pyspark_config/__init__.py
pyspark_config/config.py
pyspark_config/errors.py
pyspark_config/input/__init__.py
pyspark_config/input/creator.py
pyspark_config/input/input.py
pyspark_config/input/source.py
pyspark_config/output/__init__.py
pyspark_config/output/output.py
pyspark_config/spark_utils/__init__.py
pyspark_config/spark_utils/dataframe_extended.py
pyspark_config/spark_utils/functions.py
pyspark_config/spark_utils/table_from_database.py
pyspark_config/transformations/__init__.py
pyspark_config/transformations/transformations.py
pyspark_config/yamlConfig/__init__.py
pyspark_config/yamlConfig/config.py
pyspark_config-0.0.2.16.dist-info/LICENSE
pyspark_config-0.0.2.16.dist-info/METADATA
pyspark_config-0.0.2.16.dist-info/WHEEL
pyspark_config-0.0.2.16.dist-info/top_level.txt
pyspark_config-0.0.2.16.dist-info/RECORD
