Metadata-Version: 2.1
Name: pyspark-config
Version: 0.0.2.16
Summary: Configurable data pipeline with Pyspark
Home-page: https://github.com/Patrizio1301/pyspark-config
Author: Patrizio Guagliardo
Author-email: patrizio.guagliardo@gmx.de
License: new BSD
Platform: UNKNOWN
Classifier: Programming Language :: Python
Classifier: Topic :: Software Development
Classifier: Topic :: Scientific/Engineering
Classifier: Operating System :: Microsoft :: Windows
Classifier: Operating System :: POSIX
Classifier: Operating System :: Unix
Classifier: Operating System :: MacOS
Classifier: Programming Language :: Python :: 3
Classifier: Programming Language :: Python :: 3.6
Classifier: Programming Language :: Python :: 3.7
Classifier: Programming Language :: Python :: 3.8
Classifier: Programming Language :: Python :: Implementation :: PyPy
Requires-Python: >=3.6
Requires-Dist: pyspark (>=2.4.5)
Requires-Dist: PyYAML (>=5.3.1)
Requires-Dist: dataclasses (>=0.0)
Requires-Dist: dataclasses-json (>=0.4.2)
Requires-Dist: marshmallow (>=3.5.2)
